httpie_kong_hmac.py
httpie_kong_hmac-0.0.6.dist-info/LICENSE
httpie_kong_hmac-0.0.6.dist-info/METADATA
httpie_kong_hmac-0.0.6.dist-info/WHEEL
httpie_kong_hmac-0.0.6.dist-info/entry_points.txt
httpie_kong_hmac-0.0.6.dist-info/top_level.txt
httpie_kong_hmac-0.0.6.dist-info/RECORD
