Metadata-Version: 2.1
Name: httpie-kong-hmac
Version: 0.0.6
Summary: Kong Hmac plugin for HTTPie.
Home-page: https://github.com/JoveYu/httpie-kong-hmac
Author: Jove Yu
Author-email: yushijun110@126.com
License: MIT
Platform: UNKNOWN
Classifier: Development Status :: 4 - Beta
Classifier: Programming Language :: Python
Classifier: Programming Language :: Python :: 3
Classifier: Programming Language :: Python :: 3.3
Classifier: Programming Language :: Python :: 3.4
Classifier: Programming Language :: Python :: 3.5
Classifier: Programming Language :: Python :: 3.6
Classifier: Intended Audience :: Developers
Classifier: Environment :: Plugins
Classifier: License :: OSI Approved :: BSD License
Classifier: Topic :: Internet :: WWW/HTTP
Classifier: Topic :: Utilities
Requires-Dist: httpie (>=0.9.7)
